qnstr_optimizer/__init__.py
qnstr_optimizer/core.py
qnstr_optimizer/optimizer.py
qnstr_optimizer-0.1.0.dist-info/licenses/LICENSE
qnstr_optimizer-0.1.0.dist-info/METADATA
qnstr_optimizer-0.1.0.dist-info/WHEEL
qnstr_optimizer-0.1.0.dist-info/top_level.txt
qnstr_optimizer-0.1.0.dist-info/RECORD
