Metadata-Version: 2.4
Name: qnstr-optimizer
Version: 0.1.0
Summary: A Quasi-Newton Subspace Trust Region Algorithm for nonmonotone variational inequalities in adversarial learning over box constraints
Requires-Python: >=3.12
License-File: LICENSE
Requires-Dist: autograd>=1.8.0
Requires-Dist: torch>=2.7.0
Dynamic: license-file
